[
  {
    "category": "Programming Languages",
    "skills": [
      "Python",
      "R",
      "Bash",
      "SQL"
    ]
  },
  {
    "category": "GIS & Remote Sensing",
    "skills": [
      "Geographic Information Systems (GIS)",
      "Remote Sensing",
      "Image Interpretation",
      "LiDAR",
      "ArcGIS",
      "QGIS",
      "Mapbox",
      "StoryMaps"
    ]
  },
  {
    "category": "Coursework",
    "skills": [
      "Lidar Remote Sensing",
      "Spatial Analysis",
      "Web Development for GIS",
      "Advanced Python Programming for GIS",
      "Spatial Modeling",
      "Spatial Databases",
      "Big Data Analytics",
      "Drones for Data Collection",
      "Image Processing"
    ]
  },
  {
    "category": "Web Development",
    "skills": [
      "HTML",
      "CSS",
      "JavaScript",
      "PHP",
      "React"
    ]
  },
  {
    "category": "Other Technical Skills",
    "skills": [
      "Lidar data collection",
      "Field work",
      "",
      "Research"
    ]
  },
  {
    "category": "Soft Skills",
    "skills": [
      "Teamwork",
      "Environmental Awareness",
      "Conservation Issues"
    ]
  },
  {
    "category": "Languages",
    "skills": [
      "French"
    ]
  },
  {
    "category": "Hobbies & Interests",
    "skills": [
      "Ultimate Frisbee",
      "Disc Golf",
      "Volleyball",
      "Backpacking",
      "Traveling"
    ]
  }
]
